django_crud_generator/__init__.py
django_crud_generator/django_crud_generator.py
django_crud_generator/bin/django-crud-generator.py
django_crud_generator/templates/conf.py.tmpl
django_crud_generator/templates/conf_initial.py.tmpl
django_crud_generator/templates/forms.py.tmpl
django_crud_generator/templates/forms_initial.py.tmpl
django_crud_generator/templates/mixins.py.tmpl
django_crud_generator/templates/mixins_initial.py.tmpl
django_crud_generator/templates/serializers.py.tmpl
django_crud_generator/templates/serializers_initial.py.tmpl
django_crud_generator/templates/tests.py.tmpl
django_crud_generator/templates/urls.py.tmpl
django_crud_generator/templates/urls_api.py.tmpl
django_crud_generator/templates/urls_api_initial.py.tmpl
django_crud_generator/templates/urls_api_urls_patch.py.tmpl
django_crud_generator/templates/urls_initial.py.tmpl
django_crud_generator/templates/urls_slug.py.tmpl
django_crud_generator/templates/urls_slug_initial.py.tmpl
django_crud_generator/templates/view.py.tmpl
django_crud_generator/templates/viewsets.py.tmpl
django_crud_generator/templates/viewsets_initial.py.tmpl
django_crud_generator-0.3.1.data/scripts/django-crud-generator.py
django_crud_generator-0.3.1.dist-info/METADATA
django_crud_generator-0.3.1.dist-info/RECORD
django_crud_generator-0.3.1.dist-info/WHEEL
django_crud_generator-0.3.1.dist-info/top_level.txt
