Metadata-Version: 2.1
Name: django-crud-generator
Version: 0.3.1
Summary: A simple scaffolding for django applications
Home-page: http://github.com/contraslash/django-crud-generator
Author: contraslash S.A.S.
Author-email: ma0@contraslash.com
License: MIT
Project-URL: Source, https://github.com/contraslash/django-crud-generator
Project-URL: Bug Reports, https://github.com/contraslash/django-crud-generator/issues
Project-URL: Contraslash, https://contraslash.com/
Keywords: django scaffolding tool
Platform: UNKNOWN
Classifier: Development Status :: 3 - Alpha
Classifier: Intended Audience :: Developers
Classifier: License :: OSI Approved :: MIT License
Classifier: Programming Language :: Python :: 3
